logshuttle/__init__.py
logshuttle-0.2.2.dist-info/DESCRIPTION.rst
logshuttle-0.2.2.dist-info/LICENSE.txt
logshuttle-0.2.2.dist-info/METADATA
logshuttle-0.2.2.dist-info/RECORD
logshuttle-0.2.2.dist-info/WHEEL
logshuttle-0.2.2.dist-info/metadata.json
logshuttle-0.2.2.dist-info/top_level.txt
