Metadata-Version: 2.0
Name: logshuttle
Version: 0.2.2
Summary: Python 3 log handler for sending log records to Google Cloud Stackdriver service as custom logs in batches.
Home-page: https://github.com/arunbala/logshuttle/
Author: Arun Bala
Author-email: arunprakashb@gmail.com
License: This is free and unencumbered software released into the public domain.
Requires-Dist: google-cloud (>=0.22.0)
Provides-Extra: test
